Metadata-Version: 1.1
Name: PySSO
Version: 0.0.1
Summary: A single sign on(sso) system
Home-page: https://github.com/alexazhou/PySSO
Author: AlexaZhou
Author-email: AlexaZhou@163.com
License: LGPL
Keywords: git pull hook
Platform: UNKNOWN
Classifier: Development Status :: 3 - Alpha
Classifier: Intended Audience :: Developers
Classifier: Topic :: Software Development :: Build Tools
Classifier: License :: OSI Approved :: GNU Lesser General Public License v3 or later (LGPLv3+)
Classifier: Programming Language :: Python :: 3
Classifier: Programming Language :: Python :: 3.3
Classifier: Programming Language :: Python :: 3.4
Classifier: Programming Language :: Python :: 3.5
